langchain_openmemory/__init__.py
langchain_openmemory/client.py
langchain_openmemory/memory.py
langchain_openmemory-1.0.0.dist-info/licenses/LICENSE
langchain_openmemory-1.0.0.dist-info/METADATA
langchain_openmemory-1.0.0.dist-info/WHEEL
langchain_openmemory-1.0.0.dist-info/top_level.txt
langchain_openmemory-1.0.0.dist-info/RECORD
