Metadata-Version: 2.4
Name: langchain-openmemory
Version: 1.0.0
Summary: One-line OpenMemory integration for LangChain with persistent, temporal, local-first memory.
Author-email: Nullure <nullurereq@gmail.com>
Project-URL: Homepage, https://github.com/nullure/langchain-openmemory
Project-URL: Repository, https://github.com/nullure/langchain-openmemory
Requires-Python: >=3.9
License-File: LICENSE
Requires-Dist: openmemory-py>=1.0.2
Requires-Dist: langchain-core>=1.1.0
Dynamic: license-file
